zhipuai_platform_video/__init__.py
zhipuai_platform_video/cache/__init__.py
zhipuai_platform_video/cache/json_pipeline_cache.py
zhipuai_platform_video/cache/pipeline_cache.py
zhipuai_platform_video/download_video.py
zhipuai_platform_video/prompt_runner.py
zhipuai_platform_video/rate_limiter.py
zhipuai_platform_video/reporting/__init__.py
zhipuai_platform_video/reporting/console_workflow_callbacks.py
zhipuai_platform_video/reporting/runner_callbacks.py
zhipuai_platform_video/result_task.py
zhipuai_platform_video/start.py
zhipuai_platform_video/storage/__init__.py
zhipuai_platform_video/storage/_typing.py
zhipuai_platform_video/storage/file_pipeline_storage.py
zhipuai_platform_video/task.py
zhipuai_platform_video/utils.py
zhipuai_platform_video/video_pull.py
zhipuai_platform_video/video_pull_runner.py
zhipuai_platform_video/video_runner.py
zhipuai_platform_video-0.0.4.dist-info/METADATA
zhipuai_platform_video-0.0.4.dist-info/WHEEL
zhipuai_platform_video-0.0.4.dist-info/RECORD
