Metadata-Version: 2.1
Name: zhipuai-platform-video
Version: 0.0.4
Summary: ZhipuAI 开放平台视频生成插件
Author: Zhipu AI
Requires-Python: >=3.10,<3.12
Classifier: Programming Language :: Python :: 3
Classifier: Programming Language :: Python :: 3.10
Classifier: Programming Language :: Python :: 3.11
Provides-Extra: cli
Provides-Extra: extended-testing
Requires-Dist: aiofiles (>=24.1.0)
Requires-Dist: datashaper (>=0.0.49)
Requires-Dist: langchain-glm (>=0.0.1)
Requires-Dist: openpyxl (>=3.1.5)
Requires-Dist: zhipuai (>=2.1.4)
